cst/__init__.py
cst/cst.py
cst/cst_old.py
cst/version.py
cst/test/clark-y.dat
cst/test/propeller.dat
cst/test/test_cst.py
cst-1.2.0.dist-info/LICENSE
cst-1.2.0.dist-info/METADATA
cst-1.2.0.dist-info/WHEEL
cst-1.2.0.dist-info/top_level.txt
cst-1.2.0.dist-info/RECORD
