Metadata-Version: 2.1
Name: cst
Version: 1.2.0
Summary: Class-Shape Transformation (CST)
Home-page: https://github.com/daniel-de-vries/cst
Author: Daniel de Vries
Author-email: danieldevries6@gmail.com
License: MIT License
Download-URL: https://github.com/daniel-de-vries/cst/v1.2.0.tar.gz
Keywords: optimization,class,shape,transformation,mathematics
Platform: UNKNOWN
Classifier: Intended Audience :: Developers
Classifier: Intended Audience :: Science/Research
Classifier: Intended Audience :: Education
Classifier: License :: OSI Approved :: MIT License
Classifier: Operating System :: POSIX :: Linux
Classifier: Operating System :: MacOS :: MacOS X
Classifier: Operating System :: Microsoft :: Windows
Classifier: Programming Language :: Python :: 3.7
Requires-Dist: numpy
Requires-Dist: scipy
Provides-Extra: test
Requires-Dist: parameterized ; extra == 'test'
